neo4j_genai/__init__.py
neo4j_genai/embedder.py
neo4j_genai/embeddings/__init__.py
neo4j_genai/embeddings/openai.py
neo4j_genai/embeddings/sentence_transformers.py
neo4j_genai/exceptions.py
neo4j_genai/experimental/__init__.py
neo4j_genai/experimental/components/__init__.py
neo4j_genai/experimental/components/embedder.py
neo4j_genai/experimental/components/entity_relation_extractor.py
neo4j_genai/experimental/components/kg_writer.py
neo4j_genai/experimental/components/pdf_loader.py
neo4j_genai/experimental/components/schema.py
neo4j_genai/experimental/components/text_splitters/__init__.py
neo4j_genai/experimental/components/text_splitters/base.py
neo4j_genai/experimental/components/text_splitters/langchain.py
neo4j_genai/experimental/components/text_splitters/llamaindex.py
neo4j_genai/experimental/components/types.py
neo4j_genai/experimental/pipeline/__init__.py
neo4j_genai/experimental/pipeline/component.py
neo4j_genai/experimental/pipeline/exceptions.py
neo4j_genai/experimental/pipeline/pipeline.py
neo4j_genai/experimental/pipeline/pipeline_graph.py
neo4j_genai/experimental/pipeline/stores.py
neo4j_genai/experimental/pipeline/types.py
neo4j_genai/filters.py
neo4j_genai/generation/__init__.py
neo4j_genai/generation/graphrag.py
neo4j_genai/generation/prompts.py
neo4j_genai/generation/types.py
neo4j_genai/indexes.py
neo4j_genai/llm/__init__.py
neo4j_genai/llm/base.py
neo4j_genai/llm/openai_llm.py
neo4j_genai/llm/types.py
neo4j_genai/neo4j_queries.py
neo4j_genai/retrievers/__init__.py
neo4j_genai/retrievers/base.py
neo4j_genai/retrievers/external/__init__.py
neo4j_genai/retrievers/external/pinecone/__init__.py
neo4j_genai/retrievers/external/pinecone/pinecone.py
neo4j_genai/retrievers/external/pinecone/types.py
neo4j_genai/retrievers/external/utils.py
neo4j_genai/retrievers/external/weaviate/__init__.py
neo4j_genai/retrievers/external/weaviate/types.py
neo4j_genai/retrievers/external/weaviate/weaviate.py
neo4j_genai/retrievers/hybrid.py
neo4j_genai-0.6.0.dist-info/LICENSE.APACHE2.txt
neo4j_genai-0.6.0.dist-info/LICENSE.PYTHON.txt
neo4j_genai-0.6.0.dist-info/LICENSE.txt
neo4j_genai-0.6.0.dist-info/METADATA
neo4j_genai-0.6.0.dist-info/NOTICE.txt
neo4j_genai-0.6.0.dist-info/WHEEL
neo4j_genai-0.6.0.dist-info/RECORD
