Metadata-Version: 2.1
Name: neo4j-genai
Version: 0.6.0
Summary: Python package to allow easy integration to Neo4j's GenAI features
Home-page: https://neo4j.com/
License: Apache License, Version 2.0
Author: Neo4j, Inc
Author-email: team-gen-ai@neo4j.com
Requires-Python: >=3.8.1,<4.0.0
Classifier: License :: Other/Proprietary License
Classifier: Programming Language :: Python :: 3
Classifier: Programming Language :: Python :: 3.9
Classifier: Programming Language :: Python :: 3.10
Classifier: Programming Language :: Python :: 3.11
Classifier: Programming Language :: Python :: 3.12
Provides-Extra: external-clients
Provides-Extra: kg-creation-tools
Requires-Dist: eval-type-backport (>=0.2.0,<0.3.0)
Requires-Dist: neo4j (>=5.17.0,<6.0.0)
Requires-Dist: pinecone-client (>=4.1.0,<5.0.0) ; extra == "external-clients"
Requires-Dist: pydantic (>=2.6.3,<3.0.0)
Requires-Dist: pygraphviz (>=1.0.0,<2.0.0) ; (python_version < "3.10") and (extra == "kg-creation-tools")
Requires-Dist: pygraphviz (>=1.13.0,<2.0.0) ; (python_version >= "3.10" and python_full_version < "4.0.0") and (extra == "kg-creation-tools")
Requires-Dist: pypdf (>=4.3.1,<5.0.0)
Requires-Dist: types-mock (>=5.1.0.20240425,<6.0.0.0)
Requires-Dist: types-requests (>=2.31.0.20240218,<3.0.0.0)
Requires-Dist: weaviate-client (>=4.6.1,<5.0.0) ; extra == "external-clients"
Project-URL: Repository, https://github.com/neo4j/neo4j-genai-python
